{"1":{"confirmation":"No","confirmationHint":"Confirm Email","hint":"ex: myname@example.com","labelAlign":"Auto","name":"to","order":"3","qid":"1","required":"No","size":"30","text":"To:","type":"control_email","validation":"Email"},"2":{"buttonAlign":"Auto","buttonStyle":"book_blue2","clear":"No","name":"submitForm","order":"5","print":"No","qid":"2","text":"Submit Form","type":"control_button"},"3":{"confirmation":"No","confirmationHint":"Confirm Email","hint":"ex: myname@example.com","labelAlign":"Auto","name":"from","order":"2","qid":"3","required":"No","size":"30","subLabel":"ornek@ornek.com","text":"From:","type":"control_email","validation":"Email"},"4":{"cols":"40","entryLimit":"None-0","labelAlign":"Auto","name":"message","order":"4","qid":"4","required":"No","rows":"6","text":"Message:","type":"control_textarea","validation":"None"},"5":{"headerType":"Large","name":"clickTo","nextButtonText":"Next","order":"1","qid":"5","text":"Tell a Friend","type":"control_head"}}